{"date":"20/01/2024","readingOfToday":{"title":"Lectura de la profecía de Jonás","book":"Jon 3, 1-5. 10","content":"En aquellos días, el Señor volvió a hablar a Jonás y le dijo: “Levántate y vete a Nínive, la gran capital, para anunciar ahí el mensaje que te voy a indicar”."},"gospelOfTheDay":{"title":"Lectura del santo evangelio según san Marcos","book":"Mc 1, 14-20","content":"Después de que arrestaron a Juan el Bautista, Jesús se fue a Galilea para predicar el Evangelio de Dios y decía: “Se ha cumplido el tiempo y el Reino de Dios ya está cerca. Arrepiéntanse y crean en el Evangelio”."}}