{"date":"19/11/2023","readingOfToday":{"title":"Del Libro de los Proverbios","book":"Primera lectura","content":"Prov 31, 10-13. 19-20. 30-31"},"gospelOfTheDay":{"title":"Lectura del santo evangelio según san Mateo","book":"Mt 25, 14-15. 19-21","content":"En aquel tiempo, Jesús dijo a sus discípulos esta parábola: \"El Reino de los cielos se parece también a un hombre que iba a salir de viaje a tierras lejanas; llamó a sus servidores de confianza y les encargó sus bienes. A uno le dio cinco talentos; a otro, dos; y a un tercero, uno, según la capacidad de cada uno, y luego se fue.  Después de mucho tiempo regresó aquel hombre y llamó a cuentas a sus servidores. Se acercó el que había recibido cinco talentos y le presentó otros cinco, diciendo: 'Señor, cinco talentos me dejaste; aquí tienes otros cinco, que con ellos he ganado'. Su señor le dijo: 'Te felicito, siervo bueno y fiel. Puesto que has sido fiel en cosas de poco valor, te confiaré cosas de mucho valor. Entra a tomar parte en la alegría de tu señor'."}}